easifem/__about__.py
easifem/__init__.py
easifem/clean.py
easifem/cmake.py
easifem/components.py
easifem/console.py
easifem/easifem.py
easifem/install.py
easifem/parsers.py
easifem/run.py
easifem/setenv.py
easifem/test.py
easifem/uninstall.py
easifem/utils_clean.py
easifem/utils_install.py
easifem/utils_run.py
easifem/utils_setenv.py
easifem/utils_uninstall.py
easifem-24.1.0.dist-info/METADATA
easifem-24.1.0.dist-info/WHEEL
easifem-24.1.0.dist-info/entry_points.txt
easifem-24.1.0.dist-info/licenses/LICENSE
easifem-24.1.0.dist-info/licenses/LICENSE.txt
easifem-24.1.0.dist-info/RECORD
