Metadata-Version: 2.1
Name: easifem
Version: 24.1.0
Summary: easifem is a command line interface for using EASIFEM library. Expandable And Scalable Infrastructure for Finite Element Methods, EASIFEM, is Modern Fortran framework for solving partial differential equations (PDEs) using finite element methods.
Project-URL: Documentation, https://github.com/vickysharma0812/easifem#readme
Project-URL: Issues, https://github.com/vickysharma0812/easifem/issues
Project-URL: Source, https://github.com/vickysharma0812/easifem
Author-email: Vikas Sharma <Vickysharma0812@gmail.com>
License-Expression: MIT
License-File: LICENSE
License-File: LICENSE.txt
Keywords: FEM,Fortran,Modern Fortran,application,cli,command line interface,easifem,engineering,finite element method,high performance computing,scientific computations,scientific library
Classifier: Development Status :: 4 - Beta
Classifier: Programming Language :: Python
Classifier: Programming Language :: Python :: 3.7
Classifier: Programming Language :: Python :: 3.8
Classifier: Programming Language :: Python :: 3.9
Classifier: Programming Language :: Python :: 3.10
Classifier: Programming Language :: Python :: 3.11
Classifier: Programming Language :: Python :: Implementation :: CPython
Classifier: Programming Language :: Python :: Implementation :: PyPy
Requires-Python: >=3.7
Requires-Dist: rich>=13
